llama_index/packs/voyage_query_engine/__init__.py
llama_index/packs/voyage_query_engine/base.py
llama_index_packs_voyage_query_engine-0.5.2.dist-info/METADATA
llama_index_packs_voyage_query_engine-0.5.2.dist-info/WHEEL
llama_index_packs_voyage_query_engine-0.5.2.dist-info/licenses/LICENSE
llama_index_packs_voyage_query_engine-0.5.2.dist-info/RECORD
