Metadata-Version: 2.4
Name: llama-index-packs-voyage-query-engine
Version: 0.5.2
Summary: llama-index packs voyage_query_engine integration
Author-email: Your Name <you@example.com>
Maintainer: Liuhong99
License-Expression: MIT
License-File: LICENSE
Keywords: embeddings,query,retrieval,voyage
Requires-Python: <4.0,>=3.9
Requires-Dist: llama-index-core<0.15,>=0.13.0
Requires-Dist: llama-index-embeddings-voyageai<0.5,>=0.4.0
Requires-Dist: llama-index-llms-openai<0.6,>=0.5.0
